ddex_builder-0.4.5.dist-info/METADATA
ddex_builder-0.4.5.dist-info/WHEEL
ddex_builder/__init__.py
ddex_builder/__pycache__/__init__.cpython-312.pyc
ddex_builder/__pycache__/__init__.cpython-38.pyc
ddex_builder/_internal.abi3.so
ddex_builder-0.4.5.dist-info/RECORD
